{
    "slug": "desigualdades",
    "topic": "Desigualdades",
    "title": "Definición de desigualdad",
    "name": "Definición de desigualdad",
    "date": "10 marzo 2021",
    "style":"bg-pinkbo",
    "src": "https://images.pexels.com/photos/3781338/pexels-photo-3781338.jpeg?auto=compress&cs=tinysrgb&dpr=2&w=500",
    "description": "<div class='max-w-3xl mx-auto'><div id='funcion'><h4 class='text-xl font-bold mb-4'>¿Que son las desigualdades?</h4><p>En el lenguaje matemáticas  las desigualdades son un enunciado de una relación de orden (mayor, mayor o igual a, menor o menor o igual que) entre dos números o expresiones algebraicas. Las desigualdades pueden plantearse como preguntas, como ecuaciones, y resolverse mediante técnicas similares, o como enunciados de hecho en forma de teoremas. </p><br/></div><section id='videoYoutube'><div class='flex my-2 justify-center'><iframe width='560' height='315' src='https://www.youtube.com/embed/gYJiD9VQeLg' frameborder='0' allow='accelerometer; autoplay; clipboard-write; encrypted-media; gyroscope; picture-in-picture' allowfullscreen></iframe></div></section><div id='funcion'><h4 class='text-xl font-bold my-4'>Definiciones principales</h4><p><span class='font-semibold'>Recta numérica: </span> representación visual del conjunto de números reales como una serie de puntos.<br/><br/><span class='font-semibold'>Desigualdad:</span>Enunciado de que de dos cantidades una es específicamente menor o mayor que otra. <br/><br/>En matemáticas, las desigualdades se utilizan para comparar el tamaño relativo de los valores. <br/> Se pueden usar para comparar números enteros, variables y varias otras expresiones algebraicas. <br/><span class='font-semibold'>Ejemplo:</span> <br/>La desigualdad del triángulo establece que la suma de las longitudes de dos lados cualesquiera de un triángulo es mayor o igual que la longitud del lado restante. <br/> El análisis matemático se basa en muchas de estas desigualdades (por ejemplo, la desigualdad de Cauchy-Schwarz) en las demostraciones de sus teoremas más importantes.</p><div class='flex my-4 justify-center'><img src='https://miprofe.com/wp-content/uploads/2016/03/Desigualdades-201x150.png' alt='desigualdades'/></div></div><div id='funcion'><h4 class='text-xl font-bold my-4'>Puntos importantes</h4><p><br/><ul><li class='list-disc list-inside'>Una desigualdad describe una relación entre dos valores diferentes.</li><li class='list-disc list-inside'>La notación a &lt; b significa que a es estrictamente menor en tamaño que b, mientras que la notación a &gt; b significa que a es estrictamente mayor que b.</li><li class='list-disc list-inside'>La noción a ≤ b significa que a es menor o igual que b, mientras que la notación a ≥ b significa que a es mayor o igual que b.</li><li class='list-disc list-inside'>Las desigualdades son particularmente útiles para resolver problemas que involucran valores mínimos o máximos posibles.</li></ul><br/></p></div><section id='videoYoutube'><div class='flex my-2 justify-center'><iframe width='560' height='315' src='https://www.youtube.com/embed/pSOLepAC1KA' frameborder='0' allow='accelerometer; autoplay; clipboard-write; encrypted-media; gyroscope; picture-in-picture' allowfullscreen></iframe></div></section><div class='overflow-hidden' id='Referencias'><h4 class='text-xl font-bold mt-8'>Referencias:</h4><ul><li>Varsitytutors. (2020). Propiedades de las desigualdades. Recuperado de: <a class='text-blue-700 underline' href='https://www.varsitytutors.com/hotmath/hotmath_help/spanish/topics/properties-of-inequality'>https://www.varsitytutors.com/hotmath/hotmath_help/spanish/topics/properties-of-inequality</a></li><li>Fortún, M. (2021, 2 marzo). Desigualdad matemática. Economipedia. Recuperado de: <a class='text-blue-700 underline' href='https://economipedia.com/definiciones/desigualdad-matematica.html#:%7E:text=Propiedades%20de%20la%20desigualdad%20matem%C3%A1tica,expresi%C3%B3n%2C%20la%20desigualdad%20se%20mantiene.'> https://economipedia.com/definiciones/desigualdad-matematica.html#:%7E:text=Propiedades%20de%20la%20desigualdad%20matem%C3%A1tica,expresi%C3%B3n%2C%20la%20desigualdad%20se%20mantiene.</a></li><li>David E. Heyd' Madrid [etc.] : MacGraw-Hill, 1998 (5ª ed.) LARSON, ROLAND E. 'Cálculo  y geometría analítica. 1 / Roland E. Larson, Robert P. Hostetler, Bruce H. Edwards </li></ul></div></div>"
}